sru/__init__.py
sru/cuda_functional.py
sru/modules.py
sru/ops.py
sru/version.py
sru/csrc/CMakeLists.txt
sru/csrc/README.md
sru/csrc/main_test_cpp.cpp
sru/csrc/sru_cpu_impl.cpp
sru/csrc/sru_cuda_impl.cpp
sru/csrc/sru_cuda_impl_dummy.cpp
sru/csrc/sru_cuda_kernel.cu
sru-2.6.0.dist-info/LICENSE
sru-2.6.0.dist-info/METADATA
sru-2.6.0.dist-info/WHEEL
sru-2.6.0.dist-info/top_level.txt
sru-2.6.0.dist-info/RECORD
