Metadata-Version: 2.1
Name: sru
Version: 2.6.0
Summary: Simple Recurrent Units for Highly Parallelizable Recurrence
Home-page: https://github.com/taolei87/sru
Author: Tao Lei, Yu Zhang, Sida I. Wang, Hui Dai and Yoav Artzi
Author-email: tao@asapp.com
License: MIT
Keywords: deep learning rnn lstm cudnn sru fast pytorch torch
Platform: UNKNOWN
Requires-Dist: torch (>=1.5.1)
Requires-Dist: ninja
